neuralpredictors/__init__.py
neuralpredictors/distributions.py
neuralpredictors/old_constraints.py
neuralpredictors/regularizers.py
neuralpredictors/utils.py
neuralpredictors/data/__init__.py
neuralpredictors/data/exceptions.py
neuralpredictors/data/samplers.py
neuralpredictors/data/transforms.py
neuralpredictors/data/utils.py
neuralpredictors/data/datasets/__init__.py
neuralpredictors/data/datasets/base.py
neuralpredictors/data/datasets/movies.py
neuralpredictors/data/datasets/old_datasets.py
neuralpredictors/data/datasets/statics/__init__.py
neuralpredictors/data/datasets/statics/base.py
neuralpredictors/data/datasets/statics/filetree.py
neuralpredictors/layers/__init__.py
neuralpredictors/layers/activations.py
neuralpredictors/layers/affine.py
neuralpredictors/layers/attention.py
neuralpredictors/layers/conv.py
neuralpredictors/layers/hermite.py
neuralpredictors/layers/squeeze_excitation.py
neuralpredictors/layers/cores/__init__.py
neuralpredictors/layers/cores/base.py
neuralpredictors/layers/cores/conv2d.py
neuralpredictors/layers/encoders/__init__.py
neuralpredictors/layers/encoders/firing_rate.py
neuralpredictors/layers/modulators/__init__.py
neuralpredictors/layers/readouts/__init__.py
neuralpredictors/layers/readouts/attention.py
neuralpredictors/layers/readouts/base.py
neuralpredictors/layers/readouts/factorized.py
neuralpredictors/layers/readouts/gaussian.py
neuralpredictors/layers/readouts/multi_readout.py
neuralpredictors/layers/readouts/old_readouts.py
neuralpredictors/layers/readouts/point_pooled.py
neuralpredictors/layers/readouts/pyramid.py
neuralpredictors/layers/shifters/__init__.py
neuralpredictors/layers/shifters/base.py
neuralpredictors/layers/shifters/mlp.py
neuralpredictors/layers/shifters/static_affine.py
neuralpredictors/measures/__init__.py
neuralpredictors/measures/functions.py
neuralpredictors/measures/modules.py
neuralpredictors/measures/np_functions.py
neuralpredictors/training/__init__.py
neuralpredictors/training/context_managers.py
neuralpredictors-0.3.0.dist-info/LICENSE
neuralpredictors-0.3.0.dist-info/METADATA
neuralpredictors-0.3.0.dist-info/WHEEL
neuralpredictors-0.3.0.dist-info/top_level.txt
neuralpredictors-0.3.0.dist-info/RECORD
